my_orbital_package-0.1.dist-info/licenses/LICENSE
wavefunction/__init__.py
wavefunction/colormap.py
wavefunction/constants.py
wavefunction/math_utils.py
wavefunction/visualization.py
wavefunction/wavefunction.py
my_orbital_package-0.1.dist-info/METADATA
my_orbital_package-0.1.dist-info/WHEEL
my_orbital_package-0.1.dist-info/top_level.txt
my_orbital_package-0.1.dist-info/RECORD
