Metadata-Version: 2.4
Name: my_orbital_package
Version: 0.1
Summary: Hydrogen atom orbital visualizer and hybrid orbital constructor
Author: Your Name
License: MIT
Classifier: Programming Language :: Python :: 3
License-File: LICENSE
Requires-Dist: numpy
Requires-Dist: sympy
Requires-Dist: matplotlib
Requires-Dist: scipy
Dynamic: author
Dynamic: classifier
Dynamic: description
Dynamic: description-content-type
Dynamic: license
Dynamic: license-file
Dynamic: requires-dist
Dynamic: summary
